pipez/__init__.py
pipez/core/__init__.py
pipez/core/batch.py
pipez/core/enums.py
pipez/core/memory.py
pipez/core/node.py
pipez/core/pipeline.py
pipez/core/queue.py
pipez/core/shared_memory.py
pipez/nodes/__init__.py
pipez/nodes/node_fastapi.py
pipez/nodes/node_onnxruntime.py
pipez/resources/__init__.py
pipez/resources/fastapi/swagger-ui-bundle.js
pipez/resources/fastapi/swagger-ui.css
pipez/resources/static/DataTables/datatables.css
pipez/resources/static/DataTables/datatables.js
pipez/resources/static/DataTables/datatables.min.css
pipez/resources/static/DataTables/datatables.min.js
pipez/resources/static/DataTables/DataTables-1.13.8/css/dataTables.bootstrap.css
pipez/resources/static/DataTables/DataTables-1.13.8/css/dataTables.bootstrap.min.css
pipez/resources/static/DataTables/DataTables-1.13.8/css/dataTables.bootstrap4.css
pipez/resources/static/DataTables/DataTables-1.13.8/css/dataTables.bootstrap4.min.css
pipez/resources/static/DataTables/DataTables-1.13.8/css/dataTables.bootstrap5.css
pipez/resources/static/DataTables/DataTables-1.13.8/css/dataTables.bootstrap5.min.css
pipez/resources/static/DataTables/DataTables-1.13.8/css/dataTables.bulma.css
pipez/resources/static/DataTables/DataTables-1.13.8/css/dataTables.bulma.min.css
pipez/resources/static/DataTables/DataTables-1.13.8/css/dataTables.dataTables.css
pipez/resources/static/DataTables/DataTables-1.13.8/css/dataTables.dataTables.min.css
pipez/resources/static/DataTables/DataTables-1.13.8/css/dataTables.foundation.css
pipez/resources/static/DataTables/DataTables-1.13.8/css/dataTables.foundation.min.css
pipez/resources/static/DataTables/DataTables-1.13.8/css/dataTables.jqueryui.css
pipez/resources/static/DataTables/DataTables-1.13.8/css/dataTables.jqueryui.min.css
pipez/resources/static/DataTables/DataTables-1.13.8/css/dataTables.semanticui.css
pipez/resources/static/DataTables/DataTables-1.13.8/css/dataTables.semanticui.min.css
pipez/resources/static/DataTables/DataTables-1.13.8/css/jquery.dataTables.css
pipez-0.0.156.dist-info/LICENSE
pipez-0.0.156.dist-info/METADATA
pipez-0.0.156.dist-info/WHEEL
pipez-0.0.156.dist-info/top_level.txt
pipez-0.0.156.dist-info/RECORD
