Metadata-Version: 2.1
Name: pipez
Version: 0.0.156
Home-page: https://github.com/tam2511/pipez
Author: Alexander Timofeev
Author-email: tam2511@mail.ru
License: GPLv3
Classifier: Programming Language :: Python :: 3.9
Classifier: Programming Language :: Python :: 3.10
Classifier: Programming Language :: Python :: 3.11
Classifier: Operating System :: OS Independent
Classifier: License :: OSI Approved :: GNU General Public License v3 (GPLv3)
Requires-Python: >=3.9
License-File: LICENSE
Requires-Dist: fastapi
Requires-Dist: Jinja2
Requires-Dist: numpy
Requires-Dist: pydantic
Requires-Dist: uvicorn
